slisemap/__init__.py
slisemap/diagnostics.py
slisemap/escape.py
slisemap/local_models.py
slisemap/loss.py
slisemap/metrics.py
slisemap/plot.py
slisemap/slipmap.py
slisemap/slisemap.py
slisemap/tuning.py
slisemap/utils.py
slisemap-1.6.2.dist-info/LICENSE
slisemap-1.6.2.dist-info/METADATA
slisemap-1.6.2.dist-info/WHEEL
slisemap-1.6.2.dist-info/top_level.txt
slisemap-1.6.2.dist-info/RECORD
