Metadata-Version: 2.1
Name: slisemap
Version: 1.6.2
Summary: SLISEMAP: Combine local explanations with supervised dimensionality reduction
Author: Lauri Seppäläinen, Jarmo Mäkelä
Author-email: Anton Björklund <anton.bjorklund@helsinki.fi>, Kai Puolamäki <kai.puolamaki@helsinki.fi>
License: MIT License
Project-URL: homepage, https://github.com/edahelsinki/slisemap
Project-URL: documentation, https://edahelsinki.github.io/slisemap
Project-URL: repository, https://github.com/edahelsinki/slisemap.git
Keywords: Explainable AI,Local explanation,Dimensionality reduction,Manifold visualization
Classifier: Programming Language :: Python :: 3
Classifier: License :: OSI Approved :: MIT License
Classifier: Operating System :: OS Independent
Classifier: Topic :: Scientific/Engineering :: Artificial Intelligence
Classifier: Topic :: Scientific/Engineering :: Visualization
Requires-Python: >=3.8
License-File: LICENSE
Requires-Dist: numpy >=1.19
Requires-Dist: torch >=1.9
Requires-Dist: scikit-learn >=0.24
Requires-Dist: matplotlib >=3.3
Requires-Dist: seaborn >=0.11
Provides-Extra: dev
Requires-Dist: pytest ; extra == 'dev'
Requires-Dist: pytest-cov ; extra == 'dev'
Requires-Dist: black[jupyter] ; extra == 'dev'
Requires-Dist: ruff ; extra == 'dev'
Requires-Dist: jupyter ; extra == 'dev'
Requires-Dist: IPython ; extra == 'dev'
Provides-Extra: tuning
Requires-Dist: scikit-optimize >=0.9 ; extra == 'tuning'
Requires-Dist: scipy >=0.17 ; extra == 'tuning'
